ovos_skill_speedtest/LICENSE
ovos_skill_speedtest/MANIFEST.in
ovos_skill_speedtest/README.md
ovos_skill_speedtest/__init__.py
ovos_skill_speedtest/requirements.txt
ovos_skill_speedtest/version.py
ovos_skill_speedtest/gui/all/wifi-speed.gif
ovos_skill_speedtest/locale/ca-es/Run.voc
ovos_skill_speedtest/locale/ca-es/Speedtest.voc
ovos_skill_speedtest/locale/ca-es/error.dialog
ovos_skill_speedtest/locale/ca-es/result.dialog
ovos_skill_speedtest/locale/ca-es/running.dialog
ovos_skill_speedtest/locale/ca-es/skill.json
ovos_skill_speedtest/locale/da-dk/Run.voc
ovos_skill_speedtest/locale/da-dk/Speedtest.voc
ovos_skill_speedtest/locale/da-dk/error.dialog
ovos_skill_speedtest/locale/da-dk/result.dialog
ovos_skill_speedtest/locale/da-dk/running.dialog
ovos_skill_speedtest/locale/da-dk/skill.json
ovos_skill_speedtest/locale/de-de/Run.voc
ovos_skill_speedtest/locale/de-de/Speedtest.voc
ovos_skill_speedtest/locale/de-de/error.dialog
ovos_skill_speedtest/locale/de-de/result.dialog
ovos_skill_speedtest/locale/de-de/running.dialog
ovos_skill_speedtest/locale/de-de/skill.json
ovos_skill_speedtest/locale/el-gr/Run.voc
ovos_skill_speedtest/locale/el-gr/Speedtest.voc
ovos_skill_speedtest/locale/el-gr/error.dialog
ovos_skill_speedtest/locale/el-gr/result.dialog
ovos_skill_speedtest/locale/el-gr/running.dialog
ovos_skill_speedtest/locale/en-us/Run.voc
ovos_skill_speedtest/locale/en-us/Speedtest.voc
ovos_skill_speedtest/locale/en-us/error.dialog
ovos_skill_speedtest/locale/en-us/result.dialog
ovos_skill_speedtest/locale/en-us/running.dialog
ovos_skill_speedtest/locale/en-us/skill.json
ovos_skill_speedtest/locale/es-es/Run.voc
ovos_skill_speedtest/locale/es-es/Speedtest.voc
ovos_skill_speedtest/locale/es-es/error.dialog
ovos_skill_speedtest/locale/es-es/result.dialog
ovos_skill_speedtest/locale/es-es/running.dialog
ovos_skill_speedtest/locale/es-lm/Run.voc
ovos_skill_speedtest/locale/es-lm/Speedtest.voc
ovos_skill_speedtest/locale/es-lm/error.dialog
ovos_skill_speedtest/ovos_skill_speedtest.egg-info/PKG-INFO
ovos_skill_speedtest/ovos_skill_speedtest.egg-info/SOURCES.txt
ovos_skill_speedtest/ovos_skill_speedtest.egg-info/dependency_links.txt
ovos_skill_speedtest/ovos_skill_speedtest.egg-info/entry_points.txt
ovos_skill_speedtest/ovos_skill_speedtest.egg-info/requires.txt
ovos_skill_speedtest/ovos_skill_speedtest.egg-info/top_level.txt
ovos_skill_speedtest-0.3.6.dist-info/LICENSE
ovos_skill_speedtest-0.3.6.dist-info/METADATA
ovos_skill_speedtest-0.3.6.dist-info/WHEEL
ovos_skill_speedtest-0.3.6.dist-info/entry_points.txt
ovos_skill_speedtest-0.3.6.dist-info/top_level.txt
ovos_skill_speedtest-0.3.6.dist-info/RECORD
