Metadata-Version: 2.1
Name: ovos-skill-speedtest
Version: 0.3.6
Summary: OVOS speedtest skill plugin
Home-page: https://github.com/OpenVoiceOS/ovos-skill-speedtest
Author: luke5sky
License: Apache-2.0
Keywords: ovos skill plugin
License-File: LICENSE
Requires-Dist: speedtest-cli
Requires-Dist: ovos-workshop<8.0.0,>=0.0.12
